qfe/__init__.py
qfe-0.1.0.dist-info/METADATA
qfe-0.1.0.dist-info/WHEEL
qfe-0.1.0.dist-info/RECORD
