Metadata-Version: 2.1
Name: qfe
Version: 0.1.0
Summary: 
Author: Azat
Author-email: 8280770+azataiot@users.noreply.github.com
Requires-Python: >=3.11,<4.0
Classifier: Programming Language :: Python :: 3
Classifier: Programming Language :: Python :: 3.11
Requires-Dist: cython (>=3.0.2,<4.0.0)
